CHANGELOG.md
README.md
pytest_mock_resources/__init__.py
pytest_mock_resources/action.py
pytest_mock_resources/cli.py
pytest_mock_resources/compat/__init__.py
pytest_mock_resources/compat/import_.py
pytest_mock_resources/compat/sqlalchemy.py
pytest_mock_resources/config.py
pytest_mock_resources/container/__init__.py
pytest_mock_resources/container/base.py
pytest_mock_resources/container/mongo.py
pytest_mock_resources/container/moto.py
pytest_mock_resources/container/mysql.py
pytest_mock_resources/container/postgres.py
pytest_mock_resources/container/redis.py
pytest_mock_resources/container/redshift.py
pytest_mock_resources/credentials.py
pytest_mock_resources/fixture/__init__.py
pytest_mock_resources/fixture/base.py
pytest_mock_resources/fixture/mongo.py
pytest_mock_resources/fixture/moto/__init__.py
pytest_mock_resources/fixture/moto/action.py
pytest_mock_resources/fixture/moto/base.py
pytest_mock_resources/fixture/mysql.py
pytest_mock_resources/fixture/postgresql.py
pytest_mock_resources/fixture/redis.py
pytest_mock_resources/fixture/redshift/__init__.py
pytest_mock_resources/fixture/redshift/udf.py
pytest_mock_resources/fixture/sqlite.py
pytest_mock_resources/hooks.py
pytest_mock_resources/patch/__init__.py
pytest_mock_resources/patch/redshift/__init__.py
pytest_mock_resources/patch/redshift/mock_s3_copy.py
pytest_mock_resources/patch/redshift/mock_s3_unload.py
pytest_mock_resources/patch/redshift/psycopg2.py
pytest_mock_resources/patch/redshift/sqlalchemy.py
pytest_mock_resources/plugin.py
pytest_mock_resources/py.typed
pytest_mock_resources/sqlalchemy.py
pytest_mock_resources-2.12.4.dist-info/LICENSE
pytest_mock_resources-2.12.4.dist-info/METADATA
pytest_mock_resources-2.12.4.dist-info/WHEEL
pytest_mock_resources-2.12.4.dist-info/entry_points.txt
pytest_mock_resources-2.12.4.dist-info/RECORD
