Metadata-Version: 2.1
Name: pytest-mock-resources
Version: 2.12.4
Summary: A pytest plugin for easily instantiating reproducible mock resources.
Home-page: https://github.com/schireson/pytest-mock-resources
License: MIT
Keywords: pytest,sqlalchemy,docker,fixture,mock
Author: Omar Khan
Author-email: oakhan3@gmail.com
Requires-Python: >=3.7,<4
Classifier: Framework :: Pytest
Classifier: License :: OSI Approved :: MIT License
Classifier: Programming Language :: Python :: 3
Classifier: Programming Language :: Python :: 3.7
Classifier: Programming Language :: Python :: 3.8
Classifier: Programming Language :: Python :: 3.9
Classifier: Programming Language :: Python :: 3.10
Classifier: Programming Language :: Python :: 3.11
Provides-Extra: docker
Provides-Extra: mongo
Provides-Extra: moto
Provides-Extra: mysql
Provides-Extra: postgres
Provides-Extra: postgres-async
Provides-Extra: postgres-binary
Provides-Extra: redis
Provides-Extra: redshift
Requires-Dist: asyncpg ; extra == "postgres-async"
Requires-Dist: boto3 ; extra == "redshift" or extra == "moto"
Requires-Dist: filelock ; extra == "docker" or extra == "postgres" or extra == "postgres-binary" or extra == "postgres-async" or extra == "redshift" or extra == "mongo" or extra == "moto" or extra == "redis" or extra == "mysql"
Requires-Dist: importlib-metadata ; python_version < "3.8"
Requires-Dist: moto ; extra == "redshift"
Requires-Dist: psycopg2 ; extra == "postgres"
Requires-Dist: psycopg2-binary ; extra == "postgres-binary"
Requires-Dist: pymongo ; extra == "mongo"
Requires-Dist: pymysql (>=1.0) ; extra == "mysql"
Requires-Dist: pytest (>=1.0)
Requires-Dist: python-on-whales (>=0.22.0) ; extra == "docker" or extra == "postgres" or extra == "postgres-binary" or extra == "postgres-async" or extra == "redshift" or extra == "mongo" or extra == "moto" or extra == "redis" or extra == "mysql"
Requires-Dist: redis ; extra == "redis"
Requires-Dist: sqlalchemy (>1.0,!=1.4.0,!=1.4.1,!=1.4.2,!=1.4.3,!=1.4.4,!=1.4.5,!=1.4.6,!=1.4.7,!=1.4.8,!=1.4.9,!=1.4.10,!=1.4.11,!=1.4.12,!=1.4.13,!=1.4.14,!=1.4.15,!=1.4.16,!=1.4.17,!=1.4.18,!=1.4.19,!=1.4.20,!=1.4.21,!=1.4.22,!=1.4.23)
Requires-Dist: sqlparse ; extra == "redshift"
Requires-Dist: typing_extensions
Project-URL: Repository, https://github.com/schireson/pytest-mock-resources
